LICENSE
MANIFEST.in
README.rst
setup.py
logbag/__init__.py
logbag/loggers.py
logbag/supervisor_eventlistener.py
logbag.egg-info/PKG-INFO
logbag.egg-info/SOURCES.txt
logbag.egg-info/dependency_links.txt
logbag.egg-info/not-zip-safe
logbag.egg-info/requires.txt
logbag.egg-info/top_level.txt